tbc_packaging_way/__init__.py
tbc_packaging_way/my_lib.py
tbc_packaging_way-0.1.0.dist-info/METADATA
tbc_packaging_way-0.1.0.dist-info/WHEEL
tbc_packaging_way-0.1.0.dist-info/RECORD
