Metadata-Version: 2.1
Name: tbc-packaging-way
Version: 0.1.0
Summary: 
Author: Gaëtan Montury
Author-email: gaetan.montury@free.fr
Requires-Python: >=3.11,<4.0
Classifier: Programming Language :: Python :: 3
Classifier: Programming Language :: Python :: 3.11
Requires-Dist: rich (>=13.3.5,<14.0.0)
